JianZhiOfferTijieItchargeFix1/README.md
JianZhiOfferTijieItchargeFix1/__init__.py
JianZhiOfferTijieItchargeFix1/__main__.py
JianZhiOfferTijieItchargeFix1/file.epub
JianZhiOfferTijieItchargeFix1/index.html
JianZhiOfferTijieItchargeFix1/css/__init__.py
JianZhiOfferTijieItchargeFix1/css/annotations.css
JianZhiOfferTijieItchargeFix1/css/main.css
JianZhiOfferTijieItchargeFix1/css/normalize.css
JianZhiOfferTijieItchargeFix1/css/popup.css
JianZhiOfferTijieItchargeFix1/font/__init__.py
JianZhiOfferTijieItchargeFix1/font/fontello.eot
JianZhiOfferTijieItchargeFix1/font/fontello.svg
JianZhiOfferTijieItchargeFix1/font/fontello.ttf
JianZhiOfferTijieItchargeFix1/font/fontello.woff
JianZhiOfferTijieItchargeFix1/img/__init__.py
JianZhiOfferTijieItchargeFix1/img/annotator-glyph-sprite.png
JianZhiOfferTijieItchargeFix1/img/annotator-icon-sprite.png
JianZhiOfferTijieItchargeFix1/img/apple-touch-icon.png
JianZhiOfferTijieItchargeFix1/img/cancelfullscreen.png
JianZhiOfferTijieItchargeFix1/img/close.png
JianZhiOfferTijieItchargeFix1/img/fullscreen.png
JianZhiOfferTijieItchargeFix1/img/loader.gif
JianZhiOfferTijieItchargeFix1/img/menu-icon.png
JianZhiOfferTijieItchargeFix1/img/save.png
JianZhiOfferTijieItchargeFix1/img/saved.png
JianZhiOfferTijieItchargeFix1/img/settings-s.png
JianZhiOfferTijieItchargeFix1/img/settings.png
JianZhiOfferTijieItchargeFix1/img/star.png
JianZhiOfferTijieItchargeFix1/js/__init__.py
JianZhiOfferTijieItchargeFix1/js/epub.js
JianZhiOfferTijieItchargeFix1/js/epub.min.js
JianZhiOfferTijieItchargeFix1/js/epub.min.map
JianZhiOfferTijieItchargeFix1/js/hooks.min.js
JianZhiOfferTijieItchargeFix1/js/hooks.min.map
JianZhiOfferTijieItchargeFix1/js/reader.js
JianZhiOfferTijieItchargeFix1/js/reader.js.map
JianZhiOfferTijieItchargeFix1/js/reader.min.js
JianZhiOfferTijieItchargeFix1/js/reader.min.map
JianZhiOfferTijieItchargeFix1/js/hooks/__init__.py
JianZhiOfferTijieItchargeFix1/js/hooks/extensions/__init__.py
JianZhiOfferTijieItchargeFix1/js/hooks/extensions/highlight.js
jian_zhi_offer_tijie_itcharge_fix1-2025.3.25.0.dist-info/METADATA
jian_zhi_offer_tijie_itcharge_fix1-2025.3.25.0.dist-info/WHEEL
jian_zhi_offer_tijie_itcharge_fix1-2025.3.25.0.dist-info/entry_points.txt
jian_zhi_offer_tijie_itcharge_fix1-2025.3.25.0.dist-info/top_level.txt
jian_zhi_offer_tijie_itcharge_fix1-2025.3.25.0.dist-info/RECORD
